ToolsFor302/ToolsFor302.py
ToolsFor302/_init_.py
ToolsFor302/dlTools.py
ToolsFor302/doseTools.py
dl/_init_.py
dl/dl.py
ToolsFor302-0.3.2.dist-info/LICENSE
ToolsFor302-0.3.2.dist-info/METADATA
ToolsFor302-0.3.2.dist-info/WHEEL
ToolsFor302-0.3.2.dist-info/top_level.txt
ToolsFor302-0.3.2.dist-info/RECORD
