Metadata-Version: 2.1
Name: ToolsFor302
Version: 0.3.2
Summary: some tools for 302
Home-page: 
Author: zengkeyao
Author-email: cengkeyao186@Gmail.com
License: MIT License
Requires-Python: >=3
License-File: LICENSE
